<?xml version="1.0"?>
<opencv_storage>
<stage4>
  <maxWeakCount>16</maxWeakCount>
  <stageThreshold>-1.7620885372161865e+00</stageThreshold>
  <weakClassifiers>
    <_>
      <internalNodes>
        0 -1 31969 -136839425 -587943790 215329663 -2137661857
        -102324747 -67089296 -12880033 -1677722069</internalNodes>
      <leafValues>
        -4.6170678734779358e-01 2.2710622847080231e-01</leafValues></_>
    <_>
      <internalNodes>
        0 -1 30885 -681520190 -235613440 -2087606015 1363628483
        -868185110 -1182111743 1217083275 63128507</internalNodes>
      <leafValues>
        -4.8225632309913635e-01 2.3602877557277679e-01</leafValues></_>
    <_>
      <internalNodes>
        0 -1 8561 -552207599 51861313 -579806881 1343298713 -457588494
        -1057961739 -794500107 -1996854369</internalNodes>
      <leafValues>
        -3.7988805770874023e-01 2.9611140489578247e-01</leafValues></_>
    <_>
      <internalNodes>
        0 -1 50483 1967223154 1428279553 269009872 355715311 2081772656
        1508598389 -2145296264 1286359295</internalNodes>
      <leafValues>
        -4.9980348348617554e-01 2.5540027022361755e-01</leafValues></_>
    <_>
      <internalNodes>
        0 -1 30912 -895769949 2041269827 1891541747 363157297
        -2138210166 -595112178 1151699195 -963754289</internalNodes>
      <leafValues>
        -3.3551579713821411e-01 3.7909463047981262e-01</leafValues></_>
    <_>
      <internalNodes>
        0 -1 23893 -102924833 108993435 1844063859 386616909 -400749152
        210520235 1327716352 -607421509</internalNodes>
      <leafValues>
        -3.7718561291694641e-01 3.1856095790863037e-01</leafValues></_>
    <_>
      <internalNodes>
        0 -1 3717 -5572707 -222202341 1409676749 969776123 -1159745574
        537264640 -738128401 857674462</internalNodes>
      <leafValues>
        -3.5979670286178589e-01 3.2777360081672668e-01</leafValues></_>
    <_>
      <internalNodes>
        0 -1 45233 -12716037 -640091564 41574139 -1574654529 -807044485
        339755012 -1493178677 -1977422086</internalNodes>
      <leafValues>
        -3.2880786061286926e-01 3.6220607161521912e-01</leafValues></_>
    <_>
      <internalNodes>
        0 -1 29006 1613006586 1916858716 -786868206 1710300928
        1146466463 174473245 489027947 1996847372</internalNodes>
      <leafValues>
        -4.9322697520256042e-01 2.3943229019641876e-01</leafValues></_>
    <_>
      <internalNodes>
        0 -1 66713 -807017753 -1001485818 -83276426 -394804017
        -2105018591 1317086290 -343042832 -244338986</internalNodes>
      <leafValues>
        -3.7076884508132935e-01 3.4555098414421082e-01</leafValues></_>
    <_>
      <internalNodes>
        0 -1 103 -23674548 -1031879040 -640217465 -821948270 808598336
        1789464608 -416993384 1934822226</internalNodes>
      <leafValues>
        -6.0267114639282227e-01 2.1596005558967590e-01</leafValues></_>
    <_>
      <internalNodes>
        0 -1 56851 -382010704 125831744 890247417 454068567 -2100657432
        -1993865143 1612196794 218704094</internalNodes>
      <leafValues>
        -5.1938533782958984e-01 2.1844297647476196e-01</leafValues></_>
    <_>
      <internalNodes>
        0 -1 48756 -1194377451 -1889662517 1276166653 -1373731953
        -275250363 -1417094584 -645313776 -4265767</internalNodes>
      <leafValues>
        -3.8454765081405640e-01 3.1730988621711731e-01</leafValues></_>
    <_>
      <internalNodes>
        0 -1 16335 1363132048 -250126286 -1827994326 1057976223
        744469928 -601799429 -1341544785 156182568</internalNodes>
      <leafValues>
        -4.3840208649635315e-01 2.9351323843002319e-01</leafValues></_>
    <_>
      <internalNodes>
        0 -1 42246 1851022460 1058057778 -2146203931 657951440
        -1067124803 -1969874624 608478325 1799357014</internalNodes>
      <leafValues>
        -5.8598738908767700e-01 1.9420422613620758e-01</leafValues></_>
    <_>
      <internalNodes>
        0 -1 55370 -315033473 -1985530834 -1107362179 288903522 38577848
        -1939292297 215188730 -1968182530</internalNodes>
      <leafValues>
        -3.1067925691604614e-01 3.8680225610733032e-01</leafValues></_></weakClassifiers></stage4>
</opencv_storage>
